<AML>
 <Item type="CommandBarSection" id="21EBCED94FF03968618120D9625E4BB8" action="add">
  <classification>Data Model</classification>
  <location keyed_name="TOC" type="cui_Location">02A5F61EF1C94C41834486FA8D76B4E1</location>
  <name>vm_Option_TOC_Content</name>
  <Relationships>
   <Item type="CommandBarSectionItem" id="867F1DB65662A7522DB6AE7E2051BDC4" action="add">
    <action>Add</action>
    <related_id keyed_name="com.aras.innovator.cui_default.toc_vm_Option_867F1DB65662A7522DB6AE7E2051BDC4" type="CommandBarItem">867F1DB65662A75299E9D85137DB46EF</related_id>
    <role keyed_name="World" type="Identity">A73B655731924CD0B027E4F4D5FCC0A9</role>
    <sort_order>128</sort_order>
    <source_id keyed_name="vm_Option_TOC_Content" type="CommandBarSection">21EBCED94FF03968618120D9625E4BB8</source_id>
   </Item>
  </Relationships>
 </Item>
</AML>